{
  "generated_at": "2026-07-22T18:54:52.143969+00:00",
  "source": "bingx-ccxt+orders",
  "repo": "vincepeng518/quant-backtest-platform",
  "count": 3,
  "fees_total": -0.0146,
  "records": [
    {
      "symbol": "GOLD",
      "side": "LONG",
      "positionAmt": 0.5438,
      "avgPrice": 4017.5,
      "exitPrice": 0.0,
      "leverage": 1000.0,
      "unrealizedProfit": 68.3366,
      "realizedProfit": 22.1365,
      "pnlRatio": 0.0,
      "positionValue": 2253.05,
      "liquidationPrice": 0.0,
      "status": "OPEN",
      "ts": 1784746492143
    },
    {
      "symbol": "JTO",
      "side": "LONG",
      "positionAmt": 482.893,
      "avgPrice": 0.5989,
      "exitPrice": 0.0,
      "leverage": 75.0,
      "unrealizedProfit": 14.5211,
      "realizedProfit": -0.0338,
      "pnlRatio": 0.0,
      "positionValue": 303.74,
      "liquidationPrice": 0.0,
      "status": "OPEN",
      "ts": 1784746492143
    },
    {
      "symbol": "BTC",
      "side": "SHORT",
      "positionAmt": 0.0211,
      "avgPrice": 65940.7,
      "exitPrice": 0.0,
      "leverage": 150.0,
      "unrealizedProfit": -0.952,
      "realizedProfit": -0.6497,
      "pnlRatio": 0.0,
      "positionValue": 1392.3,
      "liquidationPrice": 0.0,
      "status": "OPEN",
      "ts": 1784746492143
    }
  ]
}